simdist-0.1.1.dist-info/METADATA
simdist-0.1.1.dist-info/WHEEL
simdist-0.1.1.dist-info/entry_points.txt
simdist-0.1.1.dist-info/licenses/LICENSE
simdist/__init__.py
simdist/core.py
simdist/dists.py
simdist-0.1.1.dist-info/RECORD
